calibrtr/CalibrtrClient.py
calibrtr/__init__.py
calibrtr-0.3.0.dist-info/LICENSE.txt
calibrtr-0.3.0.dist-info/METADATA
calibrtr-0.3.0.dist-info/WHEEL
calibrtr-0.3.0.dist-info/top_level.txt
calibrtr-0.3.0.dist-info/RECORD
