Metadata-Version: 2.1
Name: calibrtr
Version: 0.3.0
Summary: Client for calibrtr.com
Home-page: 
Author: Tom Fitzsimmons
Author-email: contact@calibrtr.com
License: MIT
License-File: LICENSE.txt
Requires-Dist: requests
